network_service_client/__init__.py
network_service_client/abstractions.py
network_service_client/client.py
network_service_client/enums.py
network_service_client/models.py
network_service_client-0.0.5.dist-info/LICENSE
network_service_client-0.0.5.dist-info/METADATA
network_service_client-0.0.5.dist-info/WHEEL
network_service_client-0.0.5.dist-info/top_level.txt
network_service_client-0.0.5.dist-info/RECORD
