Metadata-Version: 2.1
Name: network_service_client
Version: 0.0.5
Summary: A small client for network service
Author-email: Iraia <iolabarrieta@izertis.com>
Classifier: Programming Language :: Python :: 3
Classifier: License :: OSI Approved :: MIT License
Classifier: Operating System :: OS Independent
Requires-Python: >=3.7
License-File: LICENSE
Requires-Dist: requests
Requires-Dist: dict-to-dataclass
